{"nodes": [{"id": "Beak", "degree": 6}, {"id": "Beescratch", "degree": 8}, {"id": "Bumper", "degree": 4}, {"id": "CCL", "degree": 3}, {"id": "Cross", "degree": 1}, {"id": "DN16", "degree": 4}, {"id": "DN21", "degree": 6}, {"id": "DN63", "degree": 5}, {"id": "Double", "degree": 6}, {"id": "Feather", "degree": 7}, {"id": "Fish", "degree": 5}, {"id": "Five", "degree": 1}, {"id": "Fork", "degree": 1}, {"id": "Gallatin", "degree": 8}, {"id": "Grin", "degree": 12}, {"id": "Haecksel", "degree": 7}, {"id": "Hook", "degree": 6}, {"id": "Jet", "degree": 9}, {"id": "Jonah", "degree": 7}, {"id": "Knit", "degree": 4}, {"id": "Kringel", "degree": 9}, {"id": "MN105", "degree": 6}, {"id": "MN23", "degree": 1}, {"id": "MN60", "degree": 3}, {"id": "MN83", "degree": 6}, {"id": "Mus", "degree": 3}, {"id": "Notch", "degree": 3}, {"id": "Number1", "degree": 5}, {"id": "Oscar", "degree": 5}, {"id": "Patchback", "degree": 9}, {"id": "PL", "degree": 5}, {"id": "Quasi", "degree": 1}, {"id": "Ripplefluke", "degree": 3}, {"id": "Scabs", "degree": 10}, {"id": "Shmuddel", "degree": 5}, {"id": "SMN5", "degree": 1}, {"id": "SN100", "degree": 7}, {"id": "SN4", "degree": 11}, {"id": "SN63", "degree": 8}, {"id": "SN89", "degree": 2}, {"id": "SN9", "degree": 8}, {"id": "SN90", "degree": 5}, {"id": "SN96", "degree": 6}, {"id": "Stripes", "degree": 7}, {"id": "Thumper", "degree": 4}, {"id": "Topless", "degree": 11}, {"id": "TR120", "degree": 2}, {"id": "TR77", "degree": 6}, {"id": "TR82", "degree": 1}, {"id": "TR88", "degree": 2}, {"id": "TR99", "degree": 7}, {"id": "Trigger", "degree": 10}, {"id": "TSN103", "degree": 4}, {"id": "TSN83", "degree": 2}, {"id": "Upbang", "degree": 7}, {"id": "Vau", "degree": 2}, {"id": "Wave", "degree": 2}, {"id": "Web", "degree": 9}, {"id": "Whitetip", "degree": 1}, {"id": "Zap", "degree": 5}, {"id": "Zig", "degree": 1}, {"id": "Zipfel", "degree": 3}], "links": [{"source": "Beak", "target": "Fish"}, {"source": "Beak", "target": "Grin"}, {"source": "Beak", "target": "Haecksel"}, {"source": "Beak", "target": "SN9"}, {"source": "Beak", "target": "SN96"}, {"source": "Beak", "target": "TR77"}, {"source": "Beescratch", "target": "Jet"}, {"source": "Beescratch", "target": "Knit"}, {"source": "Beescratch", "target": "Notch"}, {"source": "Beescratch", "target": "Number1"}, {"source": "Beescratch", "target": "Oscar"}, {"source": "Beescratch", "target": "SN100"}, {"source": "Beescratch", "target": "SN90"}, {"source": "Beescratch", "target": "Upbang"}, {"source": "Bumper", "target": "Fish"}, {"source": "Bumper", "target": "SN96"}, {"source": "Bumper", "target": "Thumper"}, {"source": "Bumper", "target": "Zipfel"}, {"source": "CCL", "target": "Double"}, {"source": "CCL", "target": "Grin"}, {"source": "CCL", "target": "Zap"}, {"source": "Cross", "target": "Trigger"}, {"source": "DN16", "target": "Feather"}, {"source": "DN16", "target": "Gallatin"}, {"source": "DN16", "target": "Wave"}, {"source": "DN16", "target": "Web"}, {"source": "DN21", "target": "Feather"}, {"source": "DN21", "target": "Gallatin"}, {"source": "DN21", "target": "Jet"}, {"source": "DN21", "target": "Upbang"}, {"source": "DN21", "target": "Wave"}, {"source": "DN21", "target": "Web"}, {"source": "DN63", "target": "Knit"}, {"source": "DN63", "target": "Number1"}, {"source": "DN63", "target": "PL"}, {"source": "DN63", "target": "SN9"}, {"source": "DN63", "target": "Upbang"}, {"source": "Double", "target": "Kringel"}, {"source": "Double", "target": "Oscar"}, {"source": "Double", "target": "SN4"}, {"source": "Double", "target": "Topless"}, {"source": "Double", "target": "Zap"}, {"source": "Feather", "target": "Gallatin"}, {"source": "Feather", "target": "Jet"}, {"source": "Feather", "target": "Ripplefluke"}, {"source": "Feather", "target": "SN90"}, {"source": "Feather", "target": "Web"}, {"source": "Fish", "target": "Patchback"}, {"source": "Fish", "target": "SN96"}, {"source": "Fish", "target": "TR77"}, {"source": "Five", "target": "Trigger"}, {"source": "Fork", "target": "Scabs"}, {"source": "Gallatin", "target": "Jet"}, {"source": "Gallatin", "target": "Ripplefluke"}, {"source": "Gallatin", "target": "SN90"}, {"source": "Gallatin", "target": "Upbang"}, {"source": "Gallatin", "target": "Web"}, {"source": "Grin", "target": "Hook"}, {"source": "Grin", "target": "MN83"}, {"source": "Grin", "target": "Scabs"}, {"source": "Grin", "target": "Shmuddel"}, {"source": "Grin", "target": "SN4"}, {"source": "Grin", "target": "SN63"}, {"source": "Grin", "target": "SN9"}, {"source": "Grin", "target": "Stripes"}, {"source": "Grin", "target": "TR99"}, {"source": "Grin", "target": "TSN103"}, {"source": "Haecksel", "target": "Jonah"}, {"source": "Haecksel", "target": "MN83"}, {"source": "Haecksel", "target": "SN9"}, {"source": "Haecksel", "target": "Topless"}, {"source": "Haecksel", "target": "Vau"}, {"source": "Haecksel", "target": "Zap"}, {"source": "Hook", "target": "Kringel"}, {"source": "Hook", "target": "Scabs"}, {"source": "Hook", "target": "SN4"}, {"source": "Hook", "target": "SN63"}, {"source": "Hook", "target": "TR99"}, {"source": "Jet", "target": "MN23"}, {"source": "Jet", "target": "Mus"}, {"source": "Jet", "target": "Number1"}, {"source": "Jet", "target": "Quasi"}, {"source": "Jet", "target": "Web"}, {"source": "Jonah", "target": "Kringel"}, {"source": "Jonah", "target": "MN105"}, {"source": "Jonah", "target": "MN83"}, {"source": "Jonah", "target": "Patchback"}, {"source": "Jonah", "target": "Topless"}, {"source": "Jonah", "target": "Trigger"}, {"source": "Knit", "target": "PL"}, {"source": "Knit", "target": "Upbang"}, {"source": "Kringel", "target": "Oscar"}, {"source": "Kringel", "target": "SN100"}, {"source": "Kringel", "target": "SN63"}, {"source": "Kringel", "target": "Thumper"}, {"source": "Kringel", "target": "TR77"}, {"source": "Kringel", "target": "TR99"}, {"source": "MN105", "target": "Patchback"}, {"source": "MN105", "target": "Scabs"}, {"source": "MN105", "target": "SN4"}, {"source": "MN105", "target": "Topless"}, {"source": "MN105", "target": "Trigger"}, {"source": "MN60", "target": "SN100"}, {"source": "MN60", "target": "Topless"}, {"source": "MN60", "target": "Trigger"}, {"source": "MN83", "target": "Patchback"}, {"source": "MN83", "target": "Topless"}, {"source": "MN83", "target": "Trigger"}, {"source": "Mus", "target": "Notch"}, {"source": "Mus", "target": "Number1"}, {"source": "Notch", "target": "Number1"}, {"source": "Oscar", "target": "PL"}, {"source": "Oscar", "target": "TR77"}, {"source": "Patchback", "target": "SMN5"}, {"source": "Patchback", "target": "Stripes"}, {"source": "Patchback", "target": "Topless"}, {"source": "Patchback", "target": "Trigger"}, {"source": "Patchback", "target": "TSN103"}, {"source": "PL", "target": "SN96"}, {"source": "PL", "target": "TR77"}, {"source": "Ripplefluke", "target": "Zig"}, {"source": "Scabs", "target": "Shmuddel"}, {"source": "Scabs", "target": "SN4"}, {"source": "Scabs", "target": "SN63"}, {"source": "Scabs", "target": "SN9"}, {"source": "Scabs", "target": "Stripes"}, {"source": "Scabs", "target": "TR99"}, {"source": "Shmuddel", "target": "SN4"}, {"source": "Shmuddel", "target": "Thumper"}, {"source": "Shmuddel", "target": "TR88"}, {"source": "SN100", "target": "SN4"}, {"source": "SN100", "target": "SN89"}, {"source": "SN100", "target": "SN9"}, {"source": "SN100", "target": "Zap"}, {"source": "SN4", "target": "SN9"}, {"source": "SN4", "target": "Stripes"}, {"source": "SN4", "target": "Topless"}, {"source": "SN4", "target": "Zipfel"}, {"source": "SN63", "target": "Stripes"}, {"source": "SN63", "target": "Thumper"}, {"source": "SN63", "target": "TSN103"}, {"source": "SN63", "target": "Whitetip"}, {"source": "SN89", "target": "Web"}, {"source": "SN9", "target": "TSN103"}, {"source": "SN90", "target": "Upbang"}, {"source": "SN90", "target": "Web"}, {"source": "SN96", "target": "TR77"}, {"source": "SN96", "target": "TR99"}, {"source": "Stripes", "target": "TR120"}, {"source": "Stripes", "target": "TSN83"}, {"source": "Topless", "target": "TR99"}, {"source": "Topless", "target": "Trigger"}, {"source": "Topless", "target": "Zap"}, {"source": "TR120", "target": "TR88"}, {"source": "TR82", "target": "Web"}, {"source": "TR99", "target": "Trigger"}, {"source": "Trigger", "target": "Vau"}, {"source": "TSN83", "target": "Zipfel"}, {"source": "Upbang", "target": "Web"}]}